safetynet/__init__.py
safetynet/safetynet.py
safetynet/safetynet_tests.py
safetynet-0.1.dist-info/DESCRIPTION.rst
safetynet-0.1.dist-info/METADATA
safetynet-0.1.dist-info/metadata.json
safetynet-0.1.dist-info/RECORD
safetynet-0.1.dist-info/top_level.txt
safetynet-0.1.dist-info/WHEEL
