Metadata-Version: 2.0
Name: safetynet
Version: 0.1
Summary: Type documentation and checking for python
Home-page: https://github.com/denniskempin/safetynet
Author: Dennis Kempin
Author-email: denniskempin@chromium.org
License: MIT
Download-URL: https://github.com/denniskempin/safetynet/tarball/0.1
Keywords: type checking,documentation
Platform: UNKNOWN
Classifier: Development Status :: 3 - Alpha
Classifier: Intended Audience :: Developers
Classifier: License :: OSI Approved :: MIT License
Classifier: Topic :: Software Development :: Documentation
Classifier: Topic :: Software Development :: Testing
Classifier: Programming Language :: Python :: 2.7
